pelican_ga_pageview/__init__.py
pelican_ga_pageview/ga_page_view.py
pelican_ga_pageview-0.1.1.dist-info/LICENSE
pelican_ga_pageview-0.1.1.dist-info/METADATA
pelican_ga_pageview-0.1.1.dist-info/WHEEL
pelican_ga_pageview-0.1.1.dist-info/top_level.txt
pelican_ga_pageview-0.1.1.dist-info/RECORD
