Metadata-Version: 2.1
Name: pelican-ga-pageview
Version: 0.1.1
Summary: Pelican google analytics plugin modified to work with nice-blog theme
Home-page: http://github.com/JWKennington/pelican-ga-pageview
Author: James W. Kennington
Author-email: jameswkennington@gmail.com
License: MIT
Platform: UNKNOWN
